oneNeuron/__init__.py
oneNeuron/perceptron.py
oneNeuron_pypi_pyanuj-0.0.2.dist-info/LICENSE
oneNeuron_pypi_pyanuj-0.0.2.dist-info/METADATA
oneNeuron_pypi_pyanuj-0.0.2.dist-info/WHEEL
oneNeuron_pypi_pyanuj-0.0.2.dist-info/top_level.txt
oneNeuron_pypi_pyanuj-0.0.2.dist-info/RECORD
