Metadata-Version: 2.1
Name: oneNeuron-pypi-pyanuj
Version: 0.0.2
Summary: It's a implimation of Perceptron.
Home-page: https://github.com/pyanuj/oneNeuron_pypi
Author: pyanuj
Author-email: y.206anuj@gmail.com
License: UNKNOWN
Project-URL: Bug Tracker, https://github.com/pyanuj/oneNeuron_pypi/issues
Platform: UNKNOWN
Classifier: Programming Language :: Python :: 3
Classifier: License :: OSI Approved :: MIT License
Classifier: Operating System :: OS Independent
Requires-Python: >=3.7
License-File: LICENSE
Requires-Dist: numpy
Requires-Dist: tqdm
